hysteria2_api/__init__.py
hysteria2_api/client.py
hysteria2_api/exceptions.py
hysteria2_api/models.py
hysteria2_api-0.1.3.dist-info/licenses/LICENSE
hysteria2_api-0.1.3.dist-info/METADATA
hysteria2_api-0.1.3.dist-info/WHEEL
hysteria2_api-0.1.3.dist-info/top_level.txt
hysteria2_api-0.1.3.dist-info/RECORD
