Metadata-Version: 2.4
Name: hysteria2-api
Version: 0.1.3
Summary: Python package for Hysteria2 proxy server API
Author-email: ReturnFI <ReturnFI@proton.me>
License: MIT
Project-URL: Homepage, https://github.com/ReturnFI/Hysteria2-API
Project-URL: Bug Tracker, https://github.com/ReturnFI/Hysteria2-API/issues
Keywords: hysteria2,proxy,api,package
Classifier: Programming Language :: Python :: 3.9
Classifier: Programming Language :: Python :: 3.10
Classifier: License :: OSI Approved :: MIT License
Classifier: Operating System :: OS Independent
Classifier: Intended Audience :: Developers
Classifier: Topic :: Internet :: Proxy Servers
Requires-Python: >=3.9
License-File: LICENSE
Requires-Dist: requests>=2.32.4
Dynamic: license-file
